odoo9_addon_business_requirement_deliverable_report-9.0.1.0.0-py2.7-nspkg.pth
odoo_addons/business_requirement_deliverable_report/__openerp__.py
odoo_addons/business_requirement_deliverable_report/__init__.py
odoo_addons/business_requirement_deliverable_report/README.rst
odoo_addons/business_requirement_deliverable_report/report/report.xml
odoo_addons/business_requirement_deliverable_report/views/report_business_requirement.xml
odoo_addons/business_requirement_deliverable_report/views/report_business_requirement_deliverable.xml
odoo_addons/business_requirement_deliverable_report/views/report_business_requirement_deliverable_resource.xml
odoo_addons/business_requirement_deliverable_report/data/br_report_paperformat.xml
odoo_addons/business_requirement_deliverable_report/static/img/bus_req_report2.png
odoo_addons/business_requirement_deliverable_report/static/img/bus_req_report3.png
odoo_addons/business_requirement_deliverable_report/static/img/bus_req_report1.png
odoo_addons/business_requirement_deliverable_report/static/description/icon.png
odoo9_addon_business_requirement_deliverable_report-9.0.1.0.0.dist-info/top_level.txt
odoo9_addon_business_requirement_deliverable_report-9.0.1.0.0.dist-info/WHEEL
odoo9_addon_business_requirement_deliverable_report-9.0.1.0.0.dist-info/RECORD
odoo9_addon_business_requirement_deliverable_report-9.0.1.0.0.dist-info/metadata.json
odoo9_addon_business_requirement_deliverable_report-9.0.1.0.0.dist-info/DESCRIPTION.rst
odoo9_addon_business_requirement_deliverable_report-9.0.1.0.0.dist-info/METADATA
odoo9_addon_business_requirement_deliverable_report-9.0.1.0.0.dist-info/namespace_packages.txt
