Metadata-Version: 2.0
Name: odoo9-addon-business-requirement-deliverable-report
Version: 9.0.1.0.0
Summary: Print the Business Requirement Document for your customers
Home-page: https://www.elico-corp.com
Author: Elico Corp
Author-email: UNKNOWN
License: AGPL-3
Platform: UNKNOWN
Requires-Dist: odoo (<9.1a,>=9.0a)
Requires-Dist: odoo9-addon-business-requirement-deliverable
Classifier: Programming Language :: Python :: 2.7
Classifier: Framework :: Odoo
Classifier: License :: OSI Approved :: GNU Affero General Public License v3
